cell_cycle_classification/__init__.py
cell_cycle_classification/__main__.py
cell_cycle_classification/base.py
cell_cycle_classification/cli.py
cell_cycle_classification/backbone/__init__.py
cell_cycle_classification/backbone/decoder_resnet.py
cell_cycle_classification/backbone/encoder_resnet.py
cell_cycle_classification/backbone/fucci_classifier.py
cell_cycle_classification/backbone/model.py
cell_cycle_classification/utils/__init__.py
cell_cycle_classification/utils/data_set.py
cell_cycle_classification/utils/euclidean_matching_metric.py
cell_cycle_classification/utils/model_params.py
cell_cycle_classification/utils/model_trainer.py
cell_cycle_classification/utils/nucleus_id_container.py
cell_cycle_classification/utils/parser.py
cell_cycle_classification/utils/tools.py
cell_cycle_classification/utils/umap_tools.py
cell_cycle_classification/utils/vae_model_manager.py
cell_cycle_classification/vae_training/__init__.py
cell_cycle_classification/vae_training/fucci_vae_config.py
cell_cycle_classification/vae_training/trainer.py
cell_cycle_classification/vae_training/training_pipeline.py
cell_cycle_classification-0.1.12.dist-info/licenses/LICENSE
cell_cycle_classification-0.1.12.dist-info/METADATA
cell_cycle_classification-0.1.12.dist-info/WHEEL
cell_cycle_classification-0.1.12.dist-info/entry_points.txt
cell_cycle_classification-0.1.12.dist-info/top_level.txt
cell_cycle_classification-0.1.12.dist-info/RECORD
