Metadata-Version: 2.4
Name: cell_cycle_classification
Version: 0.1.12
Summary: Awesome cell_cycle_classification created by 15bonte
Home-page: https://github.com/15bonte/cell_cycle_classification/
Author: 15bonte
License-File: LICENSE
Requires-Dist: cnn_framework
Requires-Dist: segmentation-models-pytorch==0.3.0
Requires-Dist: pythae
Requires-Dist: pytorch_metric_learning
Requires-Dist: umap-learn
Requires-Dist: umap-learn[plot]
Requires-Dist: plotly
Requires-Dist: huggingface_hub
Provides-Extra: test
Requires-Dist: pytest; extra == "test"
Requires-Dist: coverage; extra == "test"
Requires-Dist: flake8; extra == "test"
Requires-Dist: black; extra == "test"
Requires-Dist: isort; extra == "test"
Requires-Dist: pytest-cov; extra == "test"
Requires-Dist: mypy; extra == "test"
Requires-Dist: gitchangelog; extra == "test"
Requires-Dist: mkdocs; extra == "test"
Dynamic: author
Dynamic: description
Dynamic: description-content-type
Dynamic: home-page
Dynamic: license-file
Dynamic: provides-extra
Dynamic: requires-dist
Dynamic: summary
